disposeexample.py
example.py
examples-summary.py
poc.py
yieldfactoryexample.py
neoteroi/di/__about__.py
neoteroi/di/__init__.py
neoteroi_di-0.0.4.dist-info/METADATA
neoteroi_di-0.0.4.dist-info/WHEEL
neoteroi_di-0.0.4.dist-info/licenses/LICENSE
neoteroi_di-0.0.4.dist-info/RECORD
