Metadata-Version: 2.1
Name: neoteroi-di
Version: 0.0.4
Summary: Implementation of dependency injection for Python 3
Project-URL: Homepage, https://github.com/Neoteroi/rodi
Project-URL: Bug Tracker, https://github.com/Neoteroi/rodi/issues
Author-email: Roberto Prevato <roberto.prevato@gmail.com>
License-File: LICENSE
Keywords: dependency,hints,injection,type,typing
Classifier: Development Status :: 3 - Alpha
Classifier: License :: OSI Approved :: MIT License
Classifier: Operating System :: OS Independent
Classifier: Programming Language :: Python :: 3
Classifier: Programming Language :: Python :: 3.7
Classifier: Programming Language :: Python :: 3.8
Classifier: Programming Language :: Python :: 3.9
Classifier: Programming Language :: Python :: 3.10
Classifier: Programming Language :: Python :: 3.11
Requires-Python: >=3.7
Requires-Dist: typing-extensions; python_version < '3.8'
